Metadata-Version: 2.1
Name: urecon
Version: 0.1.1
Summary: Find usernames across over 70 social networks
Home-page: https://github.com/s4w3d0ff/userrecon
Author: s4w3d0ff
License: GPL v3
Keywords: username,socialmedia,social,media,network,account
Platform: UNKNOWN
Classifier: Operating System :: MacOS :: MacOS X
Classifier: Operating System :: Microsoft :: Windows
Classifier: Operating System :: POSIX
Classifier: License :: OSI Approved :: GNU General Public License v3 (GPLv3)
Classifier: Programming Language :: Python :: 3
Classifier: Programming Language :: Python :: 2
